README.rst
git_ready.py
setup.py
git_ready.egg-info/PKG-INFO
git_ready.egg-info/SOURCES.txt
git_ready.egg-info/dependency_links.txt
git_ready.egg-info/entry_points.txt
git_ready.egg-info/top_level.txt