Metadata-Version: 1.1
Name: git-ready
Version: 1.1.2
Summary: Get ready to commit, socially.
Home-page: http://github.com/dolph/git-ready
Author: Dolph Mathews
Author-email: dolph.mathews@gmail.com
License: UNKNOWN
Platform: UNKNOWN
Classifier: Development Status :: 5 - Production/Stable
Classifier: Environment :: Console
Classifier: Intended Audience :: Developers
Classifier: Programming Language :: Python :: 2
Classifier: Programming Language :: Python :: 3
Classifier: Topic :: Utilities
